{"explains":[],"count":15,"quotes":[{"exchange":"NMS","shortname":"Tesla, Inc.","quoteType":"EQUITY","symbol":"TSLA","index":"quotes","score":2525665.0,"typeDisp":"Equity","longname":"Tesla, Inc.","exchDisp":"NASDAQ","isYahooFinance":true},{"exchange":"NEO","shortname":"TESLA, INC. CDR (CAD HEDGED)","quoteType":"EQUITY","symbol":"TSLA.NE","index":"quotes","score":22914.0,"typeDisp":"Equity","longname":"Tesla, Inc.","exchDisp":"NEO","isYahooFinance":true},{"exchange":"GER","shortname":"TESLA INC","quoteType":"EQUITY","symbol":"TL0.DE","index":"quotes","score":22062.0,"typeDisp":"Equity","longname":"Tesla, Inc.","exchDisp":"XETRA","isYahooFinance":true},{"exchange":"FRA","shortname":"TESLA INC","quoteType":"EQUITY","symbol":"TL0.F","index":"quotes","score":21191.0,"typeDisp":"Equity","longname":"Tesla, Inc.","exchDisp":"Frankfurt","isYahooFinance":true},{"exchange":"LSE","shortname":"GRANITESHARES FINANCIAL PLC GRA","quoteType":"EQUITY","symbol":"3LTS.L","index":"quotes","score":21091.0,"typeDisp":"Equity","longname":"Graniteshares Financial PLC - 3X Long Tesla Daily ETP","exchDisp":"London","isYahooFinance":true},{"exchange":"LSE","shortname":"LEVERAGE SHARES PUBLIC LIMITED ","quoteType":"EQUITY","symbol":"TSL3.L","index":"quotes","score":21001.0,"typeDisp":"Equity","longname":"Leverage Shares 3x Tesla ETP","exchDisp":"London","isYahooFinance":true},{"exchange":"MEX","shortname":"TESLA INC","quoteType":"EQUITY","symbol":"TSLA.MX","index":"quotes","score":20567.0,"typeDisp":"Equity","longname":"Tesla, Inc.","exchDisp":"Mexico","isYahooFinance":true}],"news":[{"uuid":"867299da-e963-344a-9a12-e22e31b1cac6","title":"Tesla’s Musk Is Selling Stock Again. We Think We Know When It Will End.","publisher":"Barrons.com","link":"https://finance.yahoo.com/m/867299da-e963-344a-9a12-e22e31b1cac6/tesla%E2%80%99s-musk-is-selling-stock.html","providerPublishTime":1637727180,"type":"STORY"},{"uuid":"2184f6ec-999d-3a6d-9e8b-c8a3003cce35","title":"Tesla employees in Germany plan works council","publisher":"Reuters","link":"https://finance.yahoo.com/news/tesla-employees-germany-plan-works-164655062.html","providerPublishTime":1637686015,"type":"STORY"},{"uuid":"603537a5-f2da-3b4b-b875-3cf89014fe43","title":"Elon Musk sells another $1 billion of Tesla stock; nearly $10 billion sold this month","publisher":"MarketWatch","link":"https://finance.yahoo.com/m/603537a5-f2da-3b4b-b875-3cf89014fe43/elon-musk-sells-another-%241.html","providerPublishTime":1637728440,"type":"STORY"},{"uuid":"8b58521a-d564-3e5c-bff4-001cbe757f6f","title":"Dow Jones Futures: These Sectors Lead Market Rotation As Tesla Falls, Software Skids; 3 Stocks In Buy Zones","publisher":"Investor's Business Daily","link":"https://finance.yahoo.com/m/8b58521a-d564-3e5c-bff4-001cbe757f6f/dow-jones-futures%3A-these.html","providerPublishTime":1637723617,"type":"STORY"},{"uuid":"99c2eba3-fefd-3d97-8fc3-252a3fbb59fc","title":"Musk Has Now Sold More Than Half the Stock He Vowed on Twitter","publisher":"Bloomberg","link":"https://finance.yahoo.com/news/musk-now-sold-more-half-032154924.html","providerPublishTime":1637728716,"type":"STORY"},{"uuid":"6f71330b-a679-3e1b-baa4-ab8376d977e6","title":"Tesla Jumps as Musk Tweets About Model S Plaid in China","publisher":"Investopedia","link":"https://finance.yahoo.com/m/6f71330b-a679-3e1b-baa4-ab8376d977e6/tesla-jumps-as-musk-tweets.html","providerPublishTime":1637619885,"type":"STORY"},{"uuid":"772810be-49a3-3214-9c90-f022aaae2d13","title":"Tesla Stock Rises As Musk Teases Model S Plaid In China; Battery Issue Drains Rivian Stock","publisher":"Investor's Business Daily","link":"https://finance.yahoo.com/m/772810be-49a3-3214-9c90-f022aaae2d13/tesla-stock-rises-as-musk.html","providerPublishTime":1637615198,"type":"STORY"},{"uuid":"3b70c839-b42a-3523-8285-7a5bc5d8312e","title":"Tesla Hired a New Lawyer. He Comes From the SEC.","publisher":"Barrons.com","link":"https://finance.yahoo.com/m/3b70c839-b42a-3523-8285-7a5bc5d8312e/tesla-hired-a-new-lawyer.-he.html","providerPublishTime":1637679600,"type":"STORY"}],"nav":[],"lists":[],"researchReports":[],"screenerFieldResults":[],"totalTime":39,"timeTakenForQuotes":422,"timeTakenForNews":600,"timeTakenForAlgowatchlist":400,"timeTakenForPredefinedScreener":400,"timeTakenForCrunchbase":0,"timeTakenForNav":400,"timeTakenForResearchReports":0,"timeTakenForScreenerField":0}
